nuclei_viewer/__init__.py
nuclei_viewer/common.py
nuclei_viewer/config.py
nuclei_viewer/config_default.ini
nuclei_viewer/helper.py
nuclei_viewer/main.py
nuclei_viewer/page_cell.py
nuclei_viewer/page_tile.py
nuclei_viewer/version.py
nuclei_viewer/assets/aixmed.png
nuclei_viewer/assets/custom_styles.css
nuclei_viewer/assets/dash_template.css
nuclei_viewer/assets/favicon.ico
nuclei_viewer/assets/logo.png
nuclei_viewer/dashx/Cropper.py
nuclei_viewer/dashx/Dropdown.py
nuclei_viewer/dashx/GraphObserver.py
nuclei_viewer/dashx/ImageBox.py
nuclei_viewer/dashx/RadioItemRows.py
nuclei_viewer/dashx/__init__.py
nuclei_viewer/dashx/_imports_.py
nuclei_viewer/dashx/dashx.css
nuclei_viewer/dashx/dashx.min.js
nuclei_viewer/dashx/metadata.json
nuclei_viewer-0.4.23.dist-info/METADATA
nuclei_viewer-0.4.23.dist-info/WHEEL
nuclei_viewer-0.4.23.dist-info/top_level.txt
nuclei_viewer-0.4.23.dist-info/RECORD
