Metadata-Version: 2.1
Name: nuclei-viewer
Version: 0.4.23
Summary: Nuclei Analysis App
Home-page: http://www.aixmed.com
Author: Jimmy Lee
Author-email: jimmy.lee@aixmed.com
License: © 2018 AIxMed, Inc. All Rights Reserved
Platform: UNKNOWN
Requires-Dist: numpy (>=1.14)
Requires-Dist: dash (>=0.26)
Requires-Dist: dash-core-components (>=0.28)
Requires-Dist: dash-html-components (>=0.11)
Requires-Dist: plotly (>=3.1)
Requires-Dist: Flask (>=1.0)
Requires-Dist: Flask-Caching (>=1.3.3)
Requires-Dist: Pillow (>=5.0)
Requires-Dist: scikit-image (==0.13.1)
Requires-Dist: opencv-python (>=3.4.0)
